[{"id": "FirearmHit_Pistol", "animal_multiplier": 2.0, "bleed_chance": 0.0, "health_damage": 13.0, "blood_damage": 0.0, "shock_damage": 15.0}, {"id": "FirearmHit_Rifle", "animal_multiplier": 2.0, "bleed_chance": 0.0, "health_damage": 13.0, "blood_damage": 0.0, "shock_damage": 15.0}, {"id": "FirearmHit_Rifle_Buttstock", "animal_multiplier": 2.0, "bleed_chance": 0.0, "health_damage": 17.0, "blood_damage": 0.0, "shock_damage": 20.0}, {"id": "FirearmHit_Rifle_Bayonet", "animal_multiplier": 2.0, "bleed_chance": 1.0, "health_damage": 20.0, "blood_damage": 100.0, "shock_damage": 7.0}, {"id": "MeleeProd", "animal_multiplier": 0.0, "bleed_chance": 0.0, "health_damage": 10.0, "blood_damage": 0.0, "shock_damage": 0.0}, {"id": "MeleeProd_Heavy", "animal_multiplier": 0.0, "bleed_chance": 0.0, "health_damage": 10.0, "blood_damage": 0.0, "shock_damage": 0.0}, {"id": "MeleeLightBlunt2", "animal_multiplier": 0.0, "bleed_chance": 0.0, "health_damage": 10.0, "blood_damage": 0.0, "shock_damage": 0.0}, {"id": "MeleeLightBlunt2_Heavy", "animal_multiplier": 0.0, "bleed_chance": 0.0, "health_damage": 10.0, "blood_damage": 0.0, "shock_damage": 0.0}, {"id": "MeleeSlash", "animal_multiplier": 5.0, "bleed_chance": 0.3, "health_damage": 15.0, "blood_damage": 100.0, "shock_damage": 0.0}, {"id": "MeleeSlash_Heavy", "animal_multiplier": 5.0, "bleed_chance": 0.3, "health_damage": 15.0, "blood_damage": 100.0, "shock_damage": 0.0}, {"id": "MeleeSlash2", "animal_multiplier": 5.0, "bleed_chance": 0.3, "health_damage": 15.0, "blood_damage": 100.0, "shock_damage": 0.0}, {"id": "MeleeSlash2_Heavy", "animal_multiplier": 5.0, "bleed_chance": 0.3, "health_damage": 15.0, "blood_damage": 100.0, "shock_damage": 0.0}, {"id": "MeleeHeavybat", "animal_multiplier": 0.0, "bleed_chance": 0.0, "health_damage": 15.0, "blood_damage": 0.0, "shock_damage": 0.0}, {"id": "MeleeHeavybat_Heavy", "animal_multiplier": 0.0, "bleed_chance": 0.0, "health_damage": 15.0, "blood_damage": 0.0, "shock_damage": 0.0}, {"id": "MeleeMeatTenderizer", "animal_multiplier": 2.0, "bleed_chance": 0.0, "health_damage": 15.0, "blood_damage": 0.0, "shock_damage": 20.0}, {"id": "MeleeMeatTenderizer_Heavy", "animal_multiplier": 2.0, "bleed_chance": 0.0, "health_damage": 15.0, "blood_damage": 0.0, "shock_damage": 20.0}, {"id": "MeleeLightBlunt", "animal_multiplier": 1.0, "bleed_chance": 0.0, "health_damage": 10.0, "blood_damage": 0.0, "shock_damage": 15.0}, {"id": "MeleeLightBlunt_Heavy", "animal_multiplier": 1.0, "bleed_chance": 0.0, "health_damage": 10.0, "blood_damage": 0.0, "shock_damage": 15.0}, {"id": "MeleeLightBluntShock", "animal_multiplier": 1.2, "bleed_chance": 0.0, "health_damage": 15.0, "blood_damage": 0.0, "shock_damage": 0.0}, {"id": "MeleeLightBluntShock_Heavy", "animal_multiplier": 1.2, "bleed_chance": 0.0, "health_damage": 15.0, "blood_damage": 0.0, "shock_damage": 0.0}, {"id": "MeleeSoft", "animal_multiplier": 0.0, "bleed_chance": 0.0, "health_damage": 5.0, "blood_damage": 0.0, "shock_damage": 5.0}, {"id": "MeleeSoft_Heavy", "animal_multiplier": 0.0, "bleed_chance": 0.0, "health_damage": 5.0, "blood_damage": 0.0, "shock_damage": 5.0}, {"id": "MeleeFist", "animal_multiplier": 0.0, "bleed_chance": 0.0, "health_damage": 10.0, "blood_damage": 0.0, "shock_damage": 15.0}, {"id": "MeleeFist_Heavy", "animal_multiplier": 0.0, "bleed_chance": 0.0, "health_damage": 13.0, "blood_damage": 0.0, "shock_damage": 15.0}, {"id": "MeleeBrassKnuckles", "animal_multiplier": 0.0, "bleed_chance": 0.0, "health_damage": 13.0, "blood_damage": 0.0, "shock_damage": 15.0}, {"id": "MeleeBrassKnuckles_Heavy", "animal_multiplier": 0.0, "bleed_chance": 0.0, "health_damage": 17.0, "blood_damage": 0.0, "shock_damage": 34.0}, {"id": "MeleeBlunt", "animal_multiplier": 1.5, "bleed_chance": 0.0, "health_damage": 15.0, "blood_damage": 0.0, "shock_damage": 20.0}, {"id": "MeleeBlunt_Heavy", "animal_multiplier": 1.5, "bleed_chance": 0.0, "health_damage": 15.0, "blood_damage": 0.0, "shock_damage": 20.0}, {"id": "MeleeBat", "animal_multiplier": 2.0, "bleed_chance": 1.0, "health_damage": 17.0, "blood_damage": 0.0, "shock_damage": 20.0}, {"id": "MeleeBat_Heavy", "animal_multiplier": 1.5, "bleed_chance": 1.0, "health_damage": 25.0, "blood_damage": 0.0, "shock_damage": 40.0}, {"id": "MeleeBatNails", "animal_multiplier": 4.0, "bleed_chance": 1.0, "health_damage": 17.0, "blood_damage": 100.0, "shock_damage": 20.0}, {"id": "MeleeBatNails_Heavy", "animal_multiplier": 1.5, "bleed_chance": 1.0, "health_damage": 25.0, "blood_damage": 100.0, "shock_damage": 40.0}, {"id": "MeleeWoodBlunt", "animal_multiplier": 2.0, "bleed_chance": 0.0, "health_damage": 15.0, "blood_damage": 0.0, "shock_damage": 20.0}, {"id": "MeleeWoodBlunt_Heavy", "animal_multiplier": 2.0, "bleed_chance": 0.0, "health_damage": 15.0, "blood_damage": 0.0, "shock_damage": 20.0}, {"id": "MeleeHatchet", "animal_multiplier": 2.0, "bleed_chance": 1.0, "health_damage": 25.0, "blood_damage": 100.0, "shock_damage": 15.0}, {"id": "MeleeHatchet_Heavy", "animal_multiplier": 2.0, "bleed_chance": 1.0, "health_damage": 34.0, "blood_damage": 100.0, "shock_damage": 15.0}, {"id": "MeleeWolf", "animal_multiplier": 5.0, "bleed_chance": 1.0, "health_damage": 20.0, "blood_damage": 100.0, "shock_damage": 12.0}, {"id": "MeleeWolf_Heavy", "animal_multiplier": 5.0, "bleed_chance": 1.0, "health_damage": 20.0, "blood_damage": 100.0, "shock_damage": 12.0}, {"id": "MeleeStab", "animal_multiplier": 2.0, "bleed_chance": 0.2, "health_damage": 15.0, "blood_damage": 100.0, "shock_damage": 10.0}, {"id": "MeleeStab_Heavy", "animal_multiplier": 2.0, "bleed_chance": 0.2, "health_damage": 15.0, "blood_damage": 100.0, "shock_damage": 10.0}, {"id": "MeleeMachete", "animal_multiplier": 3.0, "bleed_chance": 1.0, "health_damage": 25.0, "blood_damage": 100.0, "shock_damage": 15.0}, {"id": "MeleeMachete_Heavy", "animal_multiplier": 3.0, "bleed_chance": 1.0, "health_damage": 34.0, "blood_damage": 100.0, "shock_damage": 15.0}, {"id": "MeleeAxe", "animal_multiplier": 4.0, "bleed_chance": 1.0, "health_damage": 34.0, "blood_damage": 100.0, "shock_damage": 15.0}, {"id": "MeleeAxe_Heavy", "animal_multiplier": 5.0, "bleed_chance": 1.0, "health_damage": 55.0, "blood_damage": 100.0, "shock_damage": 20.0}, {"id": "MeleeSword", "animal_multiplier": 5.0, "bleed_chance": 1.0, "health_damage": 34.0, "blood_damage": 100.0, "shock_damage": 15.0}, {"id": "MeleeSword_Heavy", "animal_multiplier": 5.0, "bleed_chance": 1.0, "health_damage": 34.0, "blood_damage": 100.0, "shock_damage": 15.0}, {"id": "MeleeFireAxe", "animal_multiplier": 4.0, "bleed_chance": 1.0, "health_damage": 34.0, "blood_damage": 100.0, "shock_damage": 15.0}, {"id": "MeleeFireAxe_Heavy", "animal_multiplier": 5.0, "bleed_chance": 1.0, "health_damage": 55.0, "blood_damage": 100.0, "shock_damage": 20.0}, {"id": "MeleePitchfork", "animal_multiplier": 2.0, "bleed_chance": 1.0, "health_damage": 25.0, "blood_damage": 100.0, "shock_damage": 20.0}, {"id": "MeleePitchfork_Heavy", "animal_multiplier": 2.0, "bleed_chance": 1.0, "health_damage": 34.0, "blood_damage": 100.0, "shock_damage": 20.0}, {"id": "MeleePickaxe", "animal_multiplier": 4.0, "bleed_chance": 1.0, "health_damage": 34.0, "blood_damage": 100.0, "shock_damage": 20.0}, {"id": "MeleePickaxe_Heavy", "animal_multiplier": 4.0, "bleed_chance": 1.0, "health_damage": 55.0, "blood_damage": 100.0, "shock_damage": 20.0}, {"id": "MeleeChainsaw", "animal_multiplier": 5.0, "bleed_chance": 1.0, "health_damage": 15.0, "blood_damage": 100.0, "shock_damage": 0.0}, {"id": "MeleeChainsaw_Heavy", "animal_multiplier": 5.0, "bleed_chance": 1.0, "health_damage": 15.0, "blood_damage": 100.0, "shock_damage": 0.0}, {"id": "MeleeSickle", "animal_multiplier": 1.5, "bleed_chance": 1.0, "health_damage": 15.0, "blood_damage": 100.0, "shock_damage": 12.0}, {"id": "MeleeSickle_Heavy", "animal_multiplier": 1.5, "bleed_chance": 1.0, "health_damage": 15.0, "blood_damage": 100.0, "shock_damage": 12.0}, {"id": "MeleeKnife", "animal_multiplier": 1.5, "bleed_chance": 1.0, "health_damage": 17.0, "blood_damage": 100.0, "shock_damage": 7.0}, {"id": "MeleeKnife_Heavy", "animal_multiplier": 1.5, "bleed_chance": 1.0, "health_damage": 25.0, "blood_damage": 100.0, "shock_damage": 12.0}, {"id": "MeleeSpear", "animal_multiplier": 1.0, "bleed_chance": 1.0, "health_damage": 20.0, "blood_damage": 100.0, "shock_damage": 15.0}, {"id": "MeleeSpear_Heavy", "animal_multiplier": 1.0, "bleed_chance": 1.0, "health_damage": 25.0, "blood_damage": 100.0, "shock_damage": 15.0}, {"id": "MeleeFieldShovel", "animal_multiplier": 1.0, "bleed_chance": 0.25, "health_damage": 15.0, "blood_damage": 100.0, "shock_damage": 12.0}, {"id": "MeleeFieldShovel_Heavy", "animal_multiplier": 1.0, "bleed_chance": 0.25, "health_damage": 15.0, "blood_damage": 100.0, "shock_damage": 12.0}, {"id": "MeleeCrowbar", "animal_multiplier": 1.5, "bleed_chance": 1.0, "health_damage": 17.0, "blood_damage": 0.0, "shock_damage": 20.0}, {"id": "MeleeCrowbar_Heavy", "animal_multiplier": 1.5, "bleed_chance": 1.0, "health_damage": 25.0, "blood_damage": 0.0, "shock_damage": 40.0}, {"id": "MeleePliers", "animal_multiplier": 1.0, "bleed_chance": 0.0, "health_damage": 10.0, "blood_damage": 0.0, "shock_damage": 10.0}, {"id": "MeleePliers_Heavy", "animal_multiplier": 2.0, "bleed_chance": 0.0, "health_damage": 13.0, "blood_damage": 0.0, "shock_damage": 15.0}, {"id": "MeleeHammer", "animal_multiplier": 2.0, "bleed_chance": 0.0, "health_damage": 13.0, "blood_damage": 0.0, "shock_damage": 15.0}, {"id": "MeleeHammer_Heavy", "animal_multiplier": 2.0, "bleed_chance": 0.0, "health_damage": 17.0, "blood_damage": 0.0, "shock_damage": 34.0}, {"id": "MeleeScrewdriver", "animal_multiplier": 1.0, "bleed_chance": 1.0, "health_damage": 13.0, "blood_damage": 100.0, "shock_damage": 10.0}, {"id": "MeleeScrewdriver_Heavy", "animal_multiplier": 1.0, "bleed_chance": 1.0, "health_damage": 17.0, "blood_damage": 100.0, "shock_damage": 10.0}, {"id": "MeleeSledgeHammer", "animal_multiplier": 3.0, "bleed_chance": 1.0, "health_damage": 25.0, "blood_damage": 0.0, "shock_damage": 50.0}, {"id": "MeleeSledgeHammer_Heavy", "animal_multiplier": 3.0, "bleed_chance": 1.0, "health_damage": 34.0, "blood_damage": 0.0, "shock_damage": 100.0}, {"id": "MeleeWrench", "animal_multiplier": 1.5, "bleed_chance": 1.0, "health_damage": 17.0, "blood_damage": 0.0, "shock_damage": 20.0}, {"id": "MeleeWrench_Heavy", "animal_multiplier": 1.5, "bleed_chance": 1.0, "health_damage": 25.0, "blood_damage": 0.0, "shock_damage": 40.0}, {"id": "MeleeFarmingHoe", "animal_multiplier": 1.0, "bleed_chance": 0.0, "health_damage": 10.0, "blood_damage": 0.0, "shock_damage": 12.0}, {"id": "MeleeFarmingHoe_Heavy", "animal_multiplier": 1.0, "bleed_chance": 0.0, "health_damage": 10.0, "blood_damage": 0.0, "shock_damage": 12.0}, {"id": "MeleeShovel", "animal_multiplier": 1.0, "bleed_chance": 0.0, "health_damage": 25.0, "blood_damage": 0.0, "shock_damage": 50.0}, {"id": "MeleeShovel_Heavy", "animal_multiplier": 1.0, "bleed_chance": 0.0, "health_damage": 34.0, "blood_damage": 0.0, "shock_damage": 100.0}, {"id": "MeleeStoneKnife", "animal_multiplier": 1.0, "bleed_chance": 1.0, "health_damage": 10.0, "blood_damage": 0.0, "shock_damage": 5.0}, {"id": "MeleeStoneKnife_Heavy", "animal_multiplier": 1.0, "bleed_chance": 1.0, "health_damage": 13.0, "blood_damage": 0.0, "shock_damage": 5.0}, {"id": "MeleeHacksaw", "animal_multiplier": 1.0, "bleed_chance": 1.0, "health_damage": 13.0, "blood_damage": 100.0, "shock_damage": 5.0}, {"id": "MeleeHacksaw_Heavy", "animal_multiplier": 1.0, "bleed_chance": 1.0, "health_damage": 13.0, "blood_damage": 100.0, "shock_damage": 5.0}, {"id": "MeleeFireExtinguisher", "animal_multiplier": 2.0, "bleed_chance": 0.0, "health_damage": 10.0, "blood_damage": 0.0, "shock_damage": 15.0}, {"id": "MeleeFireExtinguisher_Heavy", "animal_multiplier": 2.0, "bleed_chance": 0.0, "health_damage": 10.0, "blood_damage": 0.0, "shock_damage": 15.0}, {"id": "MeleePipeWrench", "animal_multiplier": 2.0, "bleed_chance": 1.0, "health_damage": 17.0, "blood_damage": 0.0, "shock_damage": 20.0}, {"id": "MeleePipeWrench_Heavy", "animal_multiplier": 2.0, "bleed_chance": 1.0, "health_damage": 25.0, "blood_damage": 0.0, "shock_damage": 34.0}]